logi_circle/__init__.py
logi_circle/activity.py
logi_circle/auth.py
logi_circle/camera.py
logi_circle/const.py
logi_circle/exception.py
logi_circle/live_stream.py
logi_circle/subscription.py
logi_circle/utils.py
logi_circle-0.2.0.dist-info/LICENSE
logi_circle-0.2.0.dist-info/METADATA
logi_circle-0.2.0.dist-info/WHEEL
logi_circle-0.2.0.dist-info/top_level.txt
logi_circle-0.2.0.dist-info/RECORD
