Metadata-Version: 2.1
Name: logi-circle
Version: 0.2.0
Summary: A Python library to communicate with Logi Circle cameras
Home-page: https://github.com/evanjd/python-logi-circle
Author: Evan Bruhn
Author-email: evan.bruhn@gmail.com
License: MIT
Keywords: logi,logi circle,logitechhome automation
Platform: UNKNOWN
Classifier: Environment :: Other Environment
Classifier: Intended Audience :: Developers
Classifier: License :: OSI Approved :: MIT License
Classifier: Operating System :: OS Independent
Classifier: Framework :: AsyncIO
Classifier: Programming Language :: Python
Classifier: Programming Language :: Python :: 3.6
Classifier: Programming Language :: Python :: 3.7
Classifier: Topic :: Home Automation
Classifier: Topic :: Software Development :: Libraries :: Python Modules
Requires-Dist: aiohttp
Requires-Dist: pytz
